./.gitignore
./PKG-INFO
./README.md
./pyproject.toml
./uv.lock
./agntcy/dir/core/v1/record_pb2.py
./agntcy/dir/core/v1/record_pb2.pyi
./agntcy/dir/core/v1/record_pb2_grpc.py
./agntcy/dir/events/v1/event_service_pb2.py
./agntcy/dir/events/v1/event_service_pb2.pyi
./agntcy/dir/events/v1/event_service_pb2_grpc.py
./agntcy/dir/routing/v1/peer_pb2.py
./agntcy/dir/routing/v1/peer_pb2.pyi
./agntcy/dir/routing/v1/peer_pb2_grpc.py
./agntcy/dir/routing/v1/publication_service_pb2.py
./agntcy/dir/routing/v1/publication_service_pb2.pyi
./agntcy/dir/routing/v1/publication_service_pb2_grpc.py
./agntcy/dir/routing/v1/record_query_pb2.py
./agntcy/dir/routing/v1/record_query_pb2.pyi
./agntcy/dir/routing/v1/record_query_pb2_grpc.py
./agntcy/dir/routing/v1/routing_service_pb2.py
./agntcy/dir/routing/v1/routing_service_pb2.pyi
./agntcy/dir/routing/v1/routing_service_pb2_grpc.py
./agntcy/dir/search/v1/record_query_pb2.py
./agntcy/dir/search/v1/record_query_pb2.pyi
./agntcy/dir/search/v1/record_query_pb2_grpc.py
./agntcy/dir/search/v1/search_service_pb2.py
./agntcy/dir/search/v1/search_service_pb2.pyi
./agntcy/dir/search/v1/search_service_pb2_grpc.py
./agntcy/dir/sign/v1/public_key_pb2.py
./agntcy/dir/sign/v1/public_key_pb2.pyi
./agntcy/dir/sign/v1/public_key_pb2_grpc.py
./agntcy/dir/sign/v1/sign_service_pb2.py
./agntcy/dir/sign/v1/sign_service_pb2.pyi
./agntcy/dir/sign/v1/sign_service_pb2_grpc.py
./agntcy/dir/sign/v1/signature_pb2.py
./agntcy/dir/sign/v1/signature_pb2.pyi
./agntcy/dir/sign/v1/signature_pb2_grpc.py
./agntcy/dir/store/v1/store_service_pb2.py
./agntcy/dir/store/v1/store_service_pb2.pyi
./agntcy/dir/store/v1/store_service_pb2_grpc.py
./agntcy/dir/store/v1/sync_service_pb2.py
./agntcy/dir/store/v1/sync_service_pb2.pyi
./agntcy/dir/store/v1/sync_service_pb2_grpc.py
./agntcy/dir_sdk/client/__init__.py
./agntcy/dir_sdk/client/client.py
./agntcy/dir_sdk/client/config.py
./agntcy/dir_sdk/client/test_client.py
./agntcy/dir_sdk/models/README.md
./agntcy/dir_sdk/models/__init__.py
agntcy_dir-0.6.0.dist-info/METADATA
agntcy_dir-0.6.0.dist-info/WHEEL
agntcy_dir-0.6.0.dist-info/RECORD
