Metadata-Version: 2.4
Name: agntcy-dir
Version: 0.6.0
Summary: Directory SDK
Requires-Python: >=3.10
Requires-Dist: grpcio>=1.74.0
Requires-Dist: spiffe-tls>=0.2.1
Requires-Dist: spiffe>=0.2.2
